llama_index/program/openai/BUILD
llama_index/program/openai/__init__.py
llama_index/program/openai/base.py
llama_index_program_openai-0.1.3.dist-info/METADATA
llama_index_program_openai-0.1.3.dist-info/WHEEL
llama_index_program_openai-0.1.3.dist-info/RECORD
